{"format":2,"version":"7.1.0","globals":"f0e884cc0634f58603d1420cff69add0","files":{"d_a7387cdb12bc308f___init___py":{"hash":"3c77fc9ef7f887ac2508d4109cf92472","index":{"nums":[0,1,0,0,0,0,0,0],"html_filename":"d_a7387cdb12bc308f___init___py.html","relative_filename":"helpers/__init__.py"}},"d_a7387cdb12bc308f_load_data_py":{"hash":"b058d7404bdee3a94af0fe84342b7416","index":{"nums":[0,1,16,0,12,0,0,0],"html_filename":"d_a7387cdb12bc308f_load_data_py.html","relative_filename":"helpers/load_data.py"}},"neural_network_py":{"hash":"cc1a56c1c2ea8093d904e09cf8806e3e","index":{"nums":[0,1,68,0,43,0,0,0],"html_filename":"neural_network_py.html","relative_filename":"neural_network.py"}},"d_a44f0ac069e85531___init___py":{"hash":"3c77fc9ef7f887ac2508d4109cf92472","index":{"nums":[0,1,0,0,0,0,0,0],"html_filename":"d_a44f0ac069e85531___init___py.html","relative_filename":"tests/__init__.py"}},"d_a44f0ac069e85531_test_neural_network_py":{"hash":"b6d956cac0fe86dba1a0cda2eab1ad4f","index":{"nums":[0,1,24,0,0,0,0,0],"html_filename":"d_a44f0ac069e85531_test_neural_network_py.html","relative_filename":"tests/test_neural_network.py"}}}}